<?xml version='1.0'?><example><link ref="PlacesAndGeography">Places &amp; Geography</link><category>Metropolitan &amp; Urban Areas </category><section-title>Metro &amp; Urban Areas</section-title><caption>get information about a metropolitan area</caption><input>Wichita metro area</input><input>Los Angeles metropolitan area</input><caption>look up particular facts for an urban area</caption><input>population of the New York City urban area</input><input>counties in the Boston metropolitan area</input><input>Pittsburgh metro per capita income</input><caption>compare metropolitan areas</caption><input>Salt Lake City metro area vs Austin metro area</input><input>population Chicago urban area vs New York urban area</input></example>