<?xml version='1.0'?><example><link ref="CultureMedia">Culture &amp; Media</link><category>Periodicals</category><section-title>Periodicals</section-title><caption>get information about a periodical</caption><input>Sports Illustrated</input><input>Idaho Statesman</input><caption>compare periodicals</caption><input>Harper's Magazine, The Atlantic</input><input>New York Times vs Wall Street Journal</input><section-title>Properties of Periodicals</section-title><caption>get a specified property of a periodical</caption><input>Road &amp; Track publisher</input><caption>do calculations with periodical properties</caption><input>circulation Scientific American Mind / High Times</input></example>