<?xml version='1.0'?><example><link ref="TechnologicalWorld">Technological World</link><category>Photography</category><section-title>Photographic Optics</section-title><caption>do f-stop arithmetic</caption><input>f-stop arithmetic 5.6</input><caption>compute subject magnification</caption><input>subject magnification 10m</input><caption>compute depth of field for photgraphic lens</caption><input>depth of field f=1m</input><caption>compute hyperfocal distance</caption><input>hyperfocal distance, f-stop 8</input><caption>compute field or angle of view</caption><input>field of view</input><input>angle of view</input><caption>compute other parameters</caption><input>numerical aperture D=30mm</input><input>spot size f/8</input></example>